my_rewards/README.md
my_rewards/rewards.json
nav_rewards-0.1.1.dist-info/licenses/LICENSE
rewards/.typed
rewards/__init__.py
rewards/_version.py
rewards/conf.py
rewards/version.py
rewards/bot/__init__.py
rewards/bot/badge.py
rewards/bot/vote.py
rewards/bot/dialogs/__init__.py
rewards/bot/dialogs/badge.py
rewards/bot/dialogs/kudos.py
rewards/bot/dialogs/vote.py
rewards/callbacks/__init__.py
rewards/callbacks/training.py
rewards/context/__init__.py
rewards/context/eval.py
rewards/docs/ddl.sql
rewards/docs/env_vars.md
rewards/docs/kudos.md
rewards/engine/__init__.py
rewards/engine/engine.py
rewards/engine/login.py
rewards/env/__init__.py
rewards/env/env.py
rewards/events/__init__.py
rewards/functions/__init__.py
rewards/functions/engagement.py
rewards/functions/rewards.py
rewards/functions/training.py
rewards/handlers/__init__.py
rewards/hierarchy/__init__.py
rewards/hierarchy/manager.py
rewards/kudos/__init__.py
rewards/kudos/handlers.py
rewards/kudos/models.py
rewards/models/__init__.py
rewards/models/adpeople.py
rewards/models/rewards.py
rewards/models/user.py
rewards/registry/__init__.py
rewards/rewards/__init__.py
rewards/rewards/base.py
rewards/rewards/challenge.py
rewards/rewards/computed.py
rewards/rewards/workflow.py
rewards/rewards/event/__init__.py
rewards/rewards/event/evt.py
rewards/rewards/nomination/__init__.py
rewards/rewards/nomination/handlers.py
rewards/rewards/nomination/helpers.py
rewards/rewards/nomination/models.py
rewards/rewards/nomination/obj.py
rewards/rewards/nomination/readme.md
rewards/rewards/nomination/rules.py
rewards/rules/__init__.py
rewards/rules/abstract.py
rewards/rules/achievement.py
rewards/rules/anniversary.py
rewards/rules/attendance.py
rewards/rules/bday.py
rewards/rules/computed.py
rewards/rules/duration.py
rewards/rules/hierarchy.py
rewards/rules/other.py
rewards/rules/random_users.py
rewards/rules/seller.py
rewards/storages/.typed
rewards/storages/__init__.py
rewards/storages/abstract.py
rewards/storages/db.py
rewards/storages/file.py
nav_rewards-0.1.1.dist-info/METADATA
nav_rewards-0.1.1.dist-info/WHEEL
nav_rewards-0.1.1.dist-info/entry_points.txt
nav_rewards-0.1.1.dist-info/top_level.txt
nav_rewards-0.1.1.dist-info/RECORD
