Metadata-Version: 2.4
Name: nav-rewards
Version: 0.1.1
Summary: Engine for sending Kudos and Rewards to users, built on top of aiohttp + navigator-api.
Author-email: Jesus Lara Gimenez <jesuslarag@gmail.com>
License-Expression: MIT
Project-URL: Homepage, https://github.com/phenobarbital/nav-rewards
Project-URL: Source, https://github.com/phenobarbital/nav-rewards
Project-URL: Tracker, https://github.com/phenobarbital/nav-rewards/issues
Project-URL: Documentation, https://github.com/phenobarbital/nav-rewards
Project-URL: Funding, https://paypal.me/phenobarbital
Project-URL: Say Thanks!, https://saythanks.io/to/phenobarbital
Keywords: asyncio,rewards,kudos,notifications,email,teams,telegram
Classifier: Development Status :: 4 - Beta
Classifier: Intended Audience :: Developers
Classifier: Intended Audience :: System Administrators
Classifier: Operating System :: OS Independent
Classifier: Programming Language :: Python :: 3 :: Only
Classifier: Programming Language :: Python :: 3.10
Classifier: Programming Language :: Python :: 3.11
Classifier: Programming Language :: Python :: 3.12
Classifier: Typing :: Typed
Classifier: Environment :: Web Environment
Classifier: Framework :: AsyncIO
Classifier: Topic :: Software Development :: Libraries :: Python Modules
Requires-Python: >=3.10.0
License-File: LICENSE
Requires-Dist: aiosmtplib>=3.0.2
Requires-Dist: python-datamodel>=0.3.12
Requires-Dist: navconfig[default]>=1.7.0
Requires-Dist: navigator-api[locale,uvloop]>=2.14.4
Requires-Dist: async-notify[all]>=1.5.1
Requires-Dist: qworker>=1.13.1
Requires-Dist: transitions==0.9.2
Requires-Dist: apscheduler>=3.11.0
Provides-Extra: events
Requires-Dist: aiormq==6.9.2; extra == "events"
Provides-Extra: all
Requires-Dist: transitions==0.9.2; extra == "all"
Requires-Dist: aiormq==6.9.2; extra == "all"
Requires-Dist: apscheduler==3.11.0; extra == "all"
Dynamic: license-file
